Workbook

Sheet 00_Readme
A1: Techcombank Credit Risk Analytics Platform - Full v3
A3: Purpose | B3: Interview-grade credit risk analytics and modelling platform for Senior Expert, Credit Risk Analytics and Modelling roles.
A4: Workflow | B4: Macro scenarios -> Loan portfolio -> PD/LGD/EAD -> IFRS9 ECL -> Stress testing -> Early warning -> Dashboard -> Management actions.
A5: Editable inputs | B5: Blue font and yellow-fill cells are user inputs. Percent variables are entered as normal numbers, e.g. 8.02 means 8.02%, not 0.0802.
A6: Production note | B6: This is a synthetic demonstration model. Replace sample loan-level data with internal bank data before business use.
A7: Package contents | B7: Excel model, CSV data, Python engines, SQL data mart, Streamlit app, Power BI specification, governance pack, interview guide.

Sheet 01_Macro_Input
A1: Vietnam Macro Data Template - User Editable
A3: year | B3: gdp_growth_pct | C3: inflation_pct | D3: policy_rate_pct | E3: usd_vnd | F3: bond_yield_10y_pct | G3: credit_growth_pct | H3: source
A4: 2020 | B4: 2.91 | C4: 3.23 | D4: 4 | E4: 23175 | F4: 3 | G4: 12.1 | H4: World Bank / SBV public references
A5: 2021 | B5: 2.58 | C5: 1.84 | D5: 4 | E5: 22840 | F5: 2.1 | G5: 13.5 | H5: World Bank / SBV public references
A6: 2022 | B6: 8.02 | C6: 3.15 | D6: 6 | E6: 23630 | F6: 4.8 | G6: 14.5 | H6: World Bank / SBV public references
A7: 2023 | B7: 5.05 | C7: 3.25 | D7: 4.5 | E7: 24265 | F7: 2.9 | G7: 13.7 | H7: World Bank / SBV public references
A8: 2024 | B8: 7.09 | C8: 3.63 | D8: 4.5 | E8: 25300 | F8: 2.8 | G8: 15.1 | H8: Public macro references / illustrative
A9: 2025 | B9: 8.02 | C9: 3.51 | D9: 4.5 | E9: 26100 | F9: 4.7 | G9: 19.01 | H9: Public macro references / illustrative
A11: Base Case | B11: Normalised planning scenario
A12: Mild Stress | B12: GDP -2.0pp; Policy rate +1.0pp; Property -5%; FX +4%
A13: Severe Stress | B13: GDP -4.0pp; Policy rate +2.0pp; Property -15%; FX +8%
A14: Note | B14: All % inputs are entered as ordinary numbers. Example: type 8.02, not 8.02%.
A15: Source URLs | B15: https://data.worldbank.org/indicator/NY.GDP.MKTP.KD.ZG?locations=VN ; https://www.sbv.gov.vn

Sheet 02_Loan_Portfolio
A1: loan_id | B1: segment | C1: industry | D1: region | E1: rating_grade | F1: outstanding_balance_vnd | G1: undrawn_commitment_vnd | H1: collateral_type | I1: ltv | J1: dscr | K1: leverage | L1: dpd | M1: rating_downgrade_notches | N1: pd_12m | O1: lgd | P1: ead_vnd | Q1: ifrs9_stage | R1: lifetime_pd | S1: ecl_vnd | T1: default_flag
A2: LN00001 | B2: Retail Mortgage | C2: Real Estate | D2: Hai Phong | E2: BB | F2: 916000000000 | G2: 57517534138 | H2: Machinery | I2: 1.1128 | J2: 2.343 | K2: 1.405 | L2: 0 | M2: 0 | N2: 0.055 | O2: 0.639471 | P2: 959138150603 | Q2: 1 | R2: 0.0825 | S2: 33733763297 | T2: 0
A3: LN00002 | B3: Large Corporate | C3: Healthcare | D3: Da Nang | E3: BBB | F3: 655000000000 | G3: 205776586672 | H3: Real Estate | I3: 0.6676 | J3: 1.628 | K3: 3.887 | L3: 0 | M3: 0 | N3: 0.02766 | O3: 0.48366 | P3: 737310634668 | Q3: 1 | R3: 0.041489 | S3: 9863587556 | T3: 0
A4: LN00003 | B4: SME | C4: Technology | D4: Can Tho | E4: B | F4: 324000000000 | G4: 80487524039 | H4: Receivables | I4: 0.9829 | J4: 1.13 | K4: 4.386 | L4: 0 | M4: 0 | N4: 0.14673 | O4: 0.593999 | P4: 356195009615 | Q4: 1 | R4: 0.220095 | S4: 31045026780 | T4: 0
A5: LN00004 | B5: SME | C5: F&B | D5: Hai Phong | E5: A | F5: 668000000000 | G5: 111276398715 | H5: Inventory | I5: 0.7912 | J5: 1.909 | K5: 4.268 | L5: 0 | M5: 0 | N5: 0.013826 | O5: 0.526927 | P5: 712510559486 | Q5: 1 | R5: 0.020739 | S5: 5190748109 | T5: 0
A6: LN00005 | B6: Large Corporate | C6: Agriculture | D6: HCMC | E6: BBB | F6: 231000000000 | G6: 23809547080 | H6: Inventory | I6: 1.0206 | J6: 1.896 | K6: 3.093 | L6: 0 | M6: 0 | N6: 0.025278 | O6: 0.607209 | P6: 240523818832 | Q6: 1 | R6: 0.037918 | S6: 3691858463 | T6: 0
A7: LN00006 | B7: Retail Mortgage | C7: Retail | D7: HCMC | E7: BBB | F7: 1078000000000 | G7: 362376400032 | H7: Cash | I7: 0.7064 | J7: 1.144 | K7: 4.005 | L7: 0 | M7: 0 | N7: 0.029129 | O7: 0.347252 | P7: 1349782300024 | Q7: 1 | R7: 0.043693 | S7: 13652958551 | T7: 0
A8: LN00007 | B8: SME | C8: Energy | D8: Hanoi | E8: BB | F8: 1565000000000 | G8: 419654425673 | H8: Receivables | I8: 0.7009 | J8: 1.883 | K8: 0.2 | L8: 35 | M8: 1 | N8: 0.100833 | O8: 0.495299 | P8: 1732861770269 | Q8: 2 | R8: 0.3025 | S8: 259631118105 | T8: 0
A9: LN00008 | B9: SME | C9: Manufacturing | D9: Da Nang | E9: BBB | F9: 2949000000000 | G9: 349530439799 | H9: Unsecured | I9: 0.7607 | J9: 1.455 | K9: 3.197 | L9: 0 | M9: 0 | N9: 0.02559 | O9: 0.716231 | P9: 3088812175919 | Q9: 1 | R9: 0.038385 | S9: 56613467813 | T9: 0
A10: LN00009 | B10: Consumer Finance | C10: Agriculture | D10: Can Tho | E10: B | F10: 4000000000 | G10: 1078100252 | H10: Cash | I10: 0.7528 | J10: 1.819 | K10: 0.549 | L10: 0 | M10: 0 | N10: 0.12 | O10: 0.36349 | P10: 4808575189 | Q10: 1 | R10: 0.18 | S10: 209744363 | T10: 0
A11: LN00010 | B11: Retail Mortgage | C11: Agriculture | D11: Dong Nai | E11: AA | F11: 2704000000000 | G11: 578323597670 | H11: Machinery | I11: 0.7113 | J11: 1.389 | K11: 2.862 | L11: 0 | M11: 0 | N11: 0.005 | O11: 0.498968 | P11: 3137742698252 | Q11: 1 | R11: 0.0075 | S11: 7828173488 | T11: 0
A12: LN00011 | B12: SME | C12: Transport | D12: Hanoi | E12: BBB | F12: 1851000000000 | G12: 100790444948 | H12: Cash | I12: 0.8788 | J12: 2.293 | K12: 2.339 | L12: 5 | M12: 0 | N12: 0.027083 | O12: 0.407567 | P12: 1891316177979 | Q12: 1 | R12: 0.040625 | S12: 20876867296 | T12: 0
A13: LN00012 | B13: SME | C13: F&B | D13: Da Nang | E13: BB | F13: 2210000000000 | G13: 131584133557 | H13: Machinery | I13: 0.9254 | J13: 2.458 | K13: 2.482 | L13: 15 | M13: 0 | N13: 0.06875 | O13: 0.573895 | P13: 2262633653422 | Q13: 1 | R13: 0.103125 | S13: 89272817336 | T13: 0
... A251: LN00250 | B251: Retail Mortgage | C251: Transport | D251: Binh Duong | E251: BB | F251: 2593000000000 | G251: 253606162658 | H251: Cash | I251: 0.8812 | J251: 2.018 | K251: 5.346 | L251: 0 | M251: 1 | N251: 0.084232 | O251: 0.408435 | P251: 2783204621993 | Q251: 1 | R251: 0.126348 | S251: 95751172574 | T251: 0

Sheet 03_PD_Model
A1: PD Model Framework and Scorecard Logic
A3: Component | B3: Variable | C3: Direction | D3: Interpretation | E3: Model Treatment | G3: Metric | H3: Prototype Result
A4: Financial strength | B4: DSCR | C4: Lower = higher risk | D4: Debt service capacity | E4: Logistic / scorecard variable | G4: AUC | H4: 0.78
A5: Leverage | B5: Debt/EBITDA | C5: Higher = higher risk | D5: Balance sheet stress | E5: Winsorised continuous variable | G5: Gini | H5: =2*H4-1 -> 0.56
A6: Behaviour | B6: DPD | C6: Higher = higher risk | D6: Payment delay signal | E6: Bucketed variable | G6: KS | H6: 0.42
A7: Rating migration | B7: Downgrade notches | C7: Higher = higher risk | D7: SICR and PD shift | E7: Ordinal variable | G7: PSI | H7: 0.08
A8: Collateral | B8: LTV | C8: Higher = higher LGD | D8: Collateral buffer | E8: LGD model input | G8: Status | H8: Pass / monitor
A9: Sector | B9: Industry stress | C9: Sector-specific | D9: Macro sensitive risk | E9: Macro overlay

Sheet 04_IFRS9_ECL
A1: loan_id | B1: stage | C1: pd_12m | D1: lifetime_pd | E1: lgd | F1: ead_vnd | G1: selected_pd | H1: ecl_vnd | I1: rule
A2: ='02_Loan_Portfolio'!A2 -> LN00001 | B2: ='02_Loan_Portfolio'!Q2 -> 1 | C2: ='02_Loan_Portfolio'!N2 -> 0.055 | D2: ='02_Loan_Portfolio'!R2 -> 0.0825 | E2: ='02_Loan_Portfolio'!O2 -> 0.639471 | F2: ='02_Loan_Portfolio'!P2 -> 959138150603 | G2: =IF(B2=1,C2,D2) -> 0.055 | H2: =G2*E2*F2 -> 3.3733757e+10 | I2: =IF(B2=1,"12M ECL","Lifetime ECL") -> 12M ECL
A3: ='02_Loan_Portfolio'!A3 -> LN00002 | B3: ='02_Loan_Portfolio'!Q3 -> 1 | C3: ='02_Loan_Portfolio'!N3 -> 0.02766 | D3: ='02_Loan_Portfolio'!R3 -> 0.041489 | E3: ='02_Loan_Portfolio'!O3 -> 0.48366 | F3: ='02_Loan_Portfolio'!P3 -> 737310634668 | G3: =IF(B3=1,C3,D3) -> 0.02766 | H3: =G3*E3*F3 -> 9.8637679e+09 | I3: =IF(B3=1,"12M ECL","Lifetime ECL") -> 12M ECL
A4: ='02_Loan_Portfolio'!A4 -> LN00003 | B4: ='02_Loan_Portfolio'!Q4 -> 1 | C4: ='02_Loan_Portfolio'!N4 -> 0.14673 | D4: ='02_Loan_Portfolio'!R4 -> 0.220095 | E4: ='02_Loan_Portfolio'!O4 -> 0.593999 | F4: ='02_Loan_Portfolio'!P4 -> 356195009615 | G4: =IF(B4=1,C4,D4) -> 0.14673 | H4: =G4*E4*F4 -> 3.1045057e+10 | I4: =IF(B4=1,"12M ECL","Lifetime ECL") -> 12M ECL
A5: ='02_Loan_Portfolio'!A5 -> LN00004 | B5: ='02_Loan_Portfolio'!Q5 -> 1 | C5: ='02_Loan_Portfolio'!N5 -> 0.013826 | D5: ='02_Loan_Portfolio'!R5 -> 0.020739 | E5: ='02_Loan_Portfolio'!O5 -> 0.526927 | F5: ='02_Loan_Portfolio'!P5 -> 712510559486 | G5: =IF(B5=1,C5,D5) -> 0.013826 | H5: =G5*E5*F5 -> 5.190848e+09 | I5: =IF(B5=1,"12M ECL","Lifetime ECL") -> 12M ECL
A6: ='02_Loan_Portfolio'!A6 -> LN00005 | B6: ='02_Loan_Portfolio'!Q6 -> 1 | C6: ='02_Loan_Portfolio'!N6 -> 0.025278 | D6: ='02_Loan_Portfolio'!R6 -> 0.037918 | E6: ='02_Loan_Portfolio'!O6 -> 0.607209 | F6: ='02_Loan_Portfolio'!P6 -> 240523818832 | G6: =IF(B6=1,C6,D6) -> 0.025278 | H6: =G6*E6*F6 -> 3.6918071e+09 | I6: =IF(B6=1,"12M ECL","Lifetime ECL") -> 12M ECL
A7: ='02_Loan_Portfolio'!A7 -> LN00006 | B7: ='02_Loan_Portfolio'!Q7 -> 1 | C7: ='02_Loan_Portfolio'!N7 -> 0.029129 | D7: ='02_Loan_Portfolio'!R7 -> 0.043693 | E7: ='02_Loan_Portfolio'!O7 -> 0.347252 | F7: ='02_Loan_Portfolio'!P7 -> 1349782300024 | G7: =IF(B7=1,C7,D7) -> 0.029129 | H7: =G7*E7*F7 -> 1.3653188e+10 | I7: =IF(B7=1,"12M ECL","Lifetime ECL") -> 12M ECL
A8: ='02_Loan_Portfolio'!A8 -> LN00007 | B8: ='02_Loan_Portfolio'!Q8 -> 2 | C8: ='02_Loan_Portfolio'!N8 -> 0.100833 | D8: ='02_Loan_Portfolio'!R8 -> 0.3025 | E8: ='02_Loan_Portfolio'!O8 -> 0.495299 | F8: ='02_Loan_Portfolio'!P8 -> 1732861770269 | G8: =IF(B8=1,C8,D8) -> 0.3025 | H8: =G8*E8*F8 -> 2.5963112e+11 | I8: =IF(B8=1,"12M ECL","Lifetime ECL") -> Lifetime ECL
A9: ='02_Loan_Portfolio'!A9 -> LN00008 | B9: ='02_Loan_Portfolio'!Q9 -> 1 | C9: ='02_Loan_Portfolio'!N9 -> 0.02559 | D9: ='02_Loan_Portfolio'!R9 -> 0.038385 | E9: ='02_Loan_Portfolio'!O9 -> 0.716231 | F9: ='02_Loan_Portfolio'!P9 -> 3088812175919 | G9: =IF(B9=1,C9,D9) -> 0.02559 | H9: =G9*E9*F9 -> 5.6612835e+10 | I9: =IF(B9=1,"12M ECL","Lifetime ECL") -> 12M ECL
A10: ='02_Loan_Portfolio'!A10 -> LN00009 | B10: ='02_Loan_Portfolio'!Q10 -> 1 | C10: ='02_Loan_Portfolio'!N10 -> 0.12 | D10: ='02_Loan_Portfolio'!R10 -> 0.18 | E10: ='02_Loan_Portfolio'!O10 -> 0.36349 | F10: ='02_Loan_Portfolio'!P10 -> 4808575189 | G10: =IF(B10=1,C10,D10) -> 0.12 | H10: =G10*E10*F10 -> 2.0974428e+08 | I10: =IF(B10=1,"12M ECL","Lifetime ECL") -> 12M ECL
A11: ='02_Loan_Portfolio'!A11 -> LN00010 | B11: ='02_Loan_Portfolio'!Q11 -> 1 | C11: ='02_Loan_Portfolio'!N11 -> 0.005 | D11: ='02_Loan_Portfolio'!R11 -> 0.0075 | E11: ='02_Loan_Portfolio'!O11 -> 0.498968 | F11: ='02_Loan_Portfolio'!P11 -> 3137742698252 | G11: =IF(B11=1,C11,D11) -> 0.005 | H11: =G11*E11*F11 -> 7.828166e+09 | I11: =IF(B11=1,"12M ECL","Lifetime ECL") -> 12M ECL
A12: ='02_Loan_Portfolio'!A12 -> LN00011 | B12: ='02_Loan_Portfolio'!Q12 -> 1 | C12: ='02_Loan_Portfolio'!N12 -> 0.027083 | D12: ='02_Loan_Portfolio'!R12 -> 0.040625 | E12: ='02_Loan_Portfolio'!O12 -> 0.407567 | F12: ='02_Loan_Portfolio'!P12 -> 1891316177979 | G12: =IF(B12=1,C12,D12) -> 0.027083 | H12: =G12*E12*F12 -> 2.0876607e+10 | I12: =IF(B12=1,"12M ECL","Lifetime ECL") -> 12M ECL
A13: ='02_Loan_Portfolio'!A13 -> LN00012 | B13: ='02_Loan_Portfolio'!Q13 -> 1 | C13: ='02_Loan_Portfolio'!N13 -> 0.06875 | D13: ='02_Loan_Portfolio'!R13 -> 0.103125 | E13: ='02_Loan_Portfolio'!O13 -> 0.573895 | F13: ='02_Loan_Portfolio'!P13 -> 2262633653422 | G13: =IF(B13=1,C13,D13) -> 0.06875 | H13: =G13*E13*F13 -> 8.9272847e+10 | I13: =IF(B13=1,"12M ECL","Lifetime ECL") -> 12M ECL
... A251: ='02_Loan_Portfolio'!A251 -> LN00250 | B251: ='02_Loan_Portfolio'!Q251 -> 1 | C251: ='02_Loan_Portfolio'!N251 -> 0.084232 | D251: ='02_Loan_Portfolio'!R251 -> 0.126348 | E251: ='02_Loan_Portfolio'!O251 -> 0.408435 | F251: ='02_Loan_Portfolio'!P251 -> 2783204621993 | G251: =IF(B251=1,C251,D251) -> 0.084232 | H251: =G251*E251*F251 -> 9.5751415e+10 | I251: =IF(B251=1,"12M ECL","Lifetime ECL") -> 12M ECL

Sheet 05_Stress_Test
A1: Macro Stress Testing Engine
A3: Scenario | B3: GDP shock pp | C3: Policy rate shock pp | D3: FX shock % | E3: Property price shock % | F3: PD multiplier | G3: LGD multiplier
A4: Base | B4: 0 | C4: 0 | D4: 0 | E4: 0 | F4: 1 | G4: 1
A5: Mild Stress | B5: -2 | C5: 1 | D5: 4 | E5: -5 | F5: 1.35 | G5: 1.1
A6: Severe Stress | B6: -4 | C6: 2 | D6: 8 | E6: -15 | F6: 1.9 | G6: 1.3
A9: Scenario | B9: Stressed PD | C9: Stressed LGD | D9: EAD VND | E9: Stressed ECL VND | F9: Increase vs Base
A10: =A4 -> Base | B10: =MIN(99%,SUMPRODUCT('02_Loan_Portfolio'!N2:N251,'02_Loan_Portfolio'!P2:P251)/SUM('02_Loan_Portfolio'!P2:P251)*F4) -> 0.08888751 | C10: =MIN(95%,SUMPRODUCT('02_Loan_Portfolio'!O2:O251,'02_Loan_Portfolio'!P2:P251)/SUM('02_Loan_Portfolio'!P2:P251)*G4) -> 0.55041643 | D10: =SUM('02_Loan_Portfolio'!P2:P251) -> 427296172686485 | E10: =B10*C10*D10 -> 2.0905528e+13 | F10: =E10/$E$10-1 -> 0
A11: =A5 -> Mild Stress | B11: =MIN(99%,SUMPRODUCT('02_Loan_Portfolio'!N2:N251,'02_Loan_Portfolio'!P2:P251)/SUM('02_Loan_Portfolio'!P2:P251)*F5) -> 0.11999814 | C11: =MIN(95%,SUMPRODUCT('02_Loan_Portfolio'!O2:O251,'02_Loan_Portfolio'!P2:P251)/SUM('02_Loan_Portfolio'!P2:P251)*G5) -> 0.60545808 | D11: =SUM('02_Loan_Portfolio'!P2:P251) -> 427296172686485 | E11: =B11*C11*D11 -> 3.1044709e+13 | F11: =E11/$E$10-1 -> 0.485
A12: =A6 -> Severe Stress | B12: =MIN(99%,SUMPRODUCT('02_Loan_Portfolio'!N2:N251,'02_Loan_Portfolio'!P2:P251)/SUM('02_Loan_Portfolio'!P2:P251)*F6) -> 0.16888627 | C12: =MIN(95%,SUMPRODUCT('02_Loan_Portfolio'!O2:O251,'02_Loan_Portfolio'!P2:P251)/SUM('02_Loan_Portfolio'!P2:P251)*G6) -> 0.71554136 | D12: =SUM('02_Loan_Portfolio'!P2:P251) -> 427296172686485 | E12: =B12*C12*D12 -> 5.1636653e+13 | F12: =E12/$E$10-1 -> 1.47

Sheet 06_Early_Warning
A1: Early Warning System - Risk Signals
A3: loan_id | B3: rating | C3: dpd | D3: dscr | E3: leverage | F3: early_warning_flag | G3: key_reason
A4: ='02_Loan_Portfolio'!A2 -> LN00001 | B4: ='02_Loan_Portfolio'!E2 -> BB | C4: ='02_Loan_Portfolio'!L2 -> 0 | D4: ='02_Loan_Portfolio'!J2 -> 2.343 | E4: ='02_Loan_Portfolio'!K2 -> 1.405 | F4: =IF(OR(C4>=30,D4<1.1,E4>5),"Red",IF(OR(C4>0,D4<1.3,E4>4),"Amber","Green")) -> Green | G4: =IF(C4>=30,"DPD deterioration",IF(D4<1.1,"DSCR weakness",IF(E4>5,"High leverage","Normal"))) -> Normal
A5: ='02_Loan_Portfolio'!A3 -> LN00002 | B5: ='02_Loan_Portfolio'!E3 -> BBB | C5: ='02_Loan_Portfolio'!L3 -> 0 | D5: ='02_Loan_Portfolio'!J3 -> 1.628 | E5: ='02_Loan_Portfolio'!K3 -> 3.887 | F5: =IF(OR(C5>=30,D5<1.1,E5>5),"Red",IF(OR(C5>0,D5<1.3,E5>4),"Amber","Green")) -> Green | G5: =IF(C5>=30,"DPD deterioration",IF(D5<1.1,"DSCR weakness",IF(E5>5,"High leverage","Normal"))) -> Normal
A6: ='02_Loan_Portfolio'!A4 -> LN00003 | B6: ='02_Loan_Portfolio'!E4 -> B | C6: ='02_Loan_Portfolio'!L4 -> 0 | D6: ='02_Loan_Portfolio'!J4 -> 1.13 | E6: ='02_Loan_Portfolio'!K4 -> 4.386 | F6: =IF(OR(C6>=30,D6<1.1,E6>5),"Red",IF(OR(C6>0,D6<1.3,E6>4),"Amber","Green")) -> Amber | G6: =IF(C6>=30,"DPD deterioration",IF(D6<1.1,"DSCR weakness",IF(E6>5,"High leverage","Normal"))) -> Normal
A7: ='02_Loan_Portfolio'!A5 -> LN00004 | B7: ='02_Loan_Portfolio'!E5 -> A | C7: ='02_Loan_Portfolio'!L5 -> 0 | D7: ='02_Loan_Portfolio'!J5 -> 1.909 | E7: ='02_Loan_Portfolio'!K5 -> 4.268 | F7: =IF(OR(C7>=30,D7<1.1,E7>5),"Red",IF(OR(C7>0,D7<1.3,E7>4),"Amber","Green")) -> Amber | G7: =IF(C7>=30,"DPD deterioration",IF(D7<1.1,"DSCR weakness",IF(E7>5,"High leverage","Normal"))) -> Normal
A8: ='02_Loan_Portfolio'!A6 -> LN00005 | B8: ='02_Loan_Portfolio'!E6 -> BBB | C8: ='02_Loan_Portfolio'!L6 -> 0 | D8: ='02_Loan_Portfolio'!J6 -> 1.896 | E8: ='02_Loan_Portfolio'!K6 -> 3.093 | F8: =IF(OR(C8>=30,D8<1.1,E8>5),"Red",IF(OR(C8>0,D8<1.3,E8>4),"Amber","Green")) -> Green | G8: =IF(C8>=30,"DPD deterioration",IF(D8<1.1,"DSCR weakness",IF(E8>5,"High leverage","Normal"))) -> Normal
A9: ='02_Loan_Portfolio'!A7 -> LN00006 | B9: ='02_Loan_Portfolio'!E7 -> BBB | C9: ='02_Loan_Portfolio'!L7 -> 0 | D9: ='02_Loan_Portfolio'!J7 -> 1.144 | E9: ='02_Loan_Portfolio'!K7 -> 4.005 | F9: =IF(OR(C9>=30,D9<1.1,E9>5),"Red",IF(OR(C9>0,D9<1.3,E9>4),"Amber","Green")) -> Amber | G9: =IF(C9>=30,"DPD deterioration",IF(D9<1.1,"DSCR weakness",IF(E9>5,"High leverage","Normal"))) -> Normal
A10: ='02_Loan_Portfolio'!A8 -> LN00007 | B10: ='02_Loan_Portfolio'!E8 -> BB | C10: ='02_Loan_Portfolio'!L8 -> 35 | D10: ='02_Loan_Portfolio'!J8 -> 1.883 | E10: ='02_Loan_Portfolio'!K8 -> 0.2 | F10: =IF(OR(C10>=30,D10<1.1,E10>5),"Red",IF(OR(C10>0,D10<1.3,E10>4),"Amber","Green")) -> Red | G10: =IF(C10>=30,"DPD deterioration",IF(D10<1.1,"DSCR weakness",IF(E10>5,"High leverage","Normal"))) -> DPD deterioration
A11: ='02_Loan_Portfolio'!A9 -> LN00008 | B11: ='02_Loan_Portfolio'!E9 -> BBB | C11: ='02_Loan_Portfolio'!L9 -> 0 | D11: ='02_Loan_Portfolio'!J9 -> 1.455 | E11: ='02_Loan_Portfolio'!K9 -> 3.197 | F11: =IF(OR(C11>=30,D11<1.1,E11>5),"Red",IF(OR(C11>0,D11<1.3,E11>4),"Amber","Green")) -> Green | G11: =IF(C11>=30,"DPD deterioration",IF(D11<1.1,"DSCR weakness",IF(E11>5,"High leverage","Normal"))) -> Normal
A12: ='02_Loan_Portfolio'!A10 -> LN00009 | B12: ='02_Loan_Portfolio'!E10 -> B | C12: ='02_Loan_Portfolio'!L10 -> 0 | D12: ='02_Loan_Portfolio'!J10 -> 1.819 | E12: ='02_Loan_Portfolio'!K10 -> 0.549 | F12: =IF(OR(C12>=30,D12<1.1,E12>5),"Red",IF(OR(C12>0,D12<1.3,E12>4),"Amber","Green")) -> Green | G12: =IF(C12>=30,"DPD deterioration",IF(D12<1.1,"DSCR weakness",IF(E12>5,"High leverage","Normal"))) -> Normal
A13: ='02_Loan_Portfolio'!A11 -> LN00010 | B13: ='02_Loan_Portfolio'!E11 -> AA | C13: ='02_Loan_Portfolio'!L11 -> 0 | D13: ='02_Loan_Portfolio'!J11 -> 1.389 | E13: ='02_Loan_Portfolio'!K11 -> 2.862 | F13: =IF(OR(C13>=30,D13<1.1,E13>5),"Red",IF(OR(C13>0,D13<1.3,E13>4),"Amber","Green")) -> Green | G13: =IF(C13>=30,"DPD deterioration",IF(D13<1.1,"DSCR weakness",IF(E13>5,"High leverage","Normal"))) -> Normal
A14: ='02_Loan_Portfolio'!A12 -> LN00011 | B14: ='02_Loan_Portfolio'!E12 -> BBB | C14: ='02_Loan_Portfolio'!L12 -> 5 | D14: ='02_Loan_Portfolio'!J12 -> 2.293 | E14: ='02_Loan_Portfolio'!K12 -> 2.339 | F14: =IF(OR(C14>=30,D14<1.1,E14>5),"Red",IF(OR(C14>0,D14<1.3,E14>4),"Amber","Green")) -> Amber | G14: =IF(C14>=30,"DPD deterioration",IF(D14<1.1,"DSCR weakness",IF(E14>5,"High leverage","Normal"))) -> Normal
A15: ='02_Loan_Portfolio'!A13 -> LN00012 | B15: ='02_Loan_Portfolio'!E13 -> BB | C15: ='02_Loan_Portfolio'!L13 -> 15 | D15: ='02_Loan_Portfolio'!J13 -> 2.458 | E15: ='02_Loan_Portfolio'!K13 -> 2.482 | F15: =IF(OR(C15>=30,D15<1.1,E15>5),"Red",IF(OR(C15>0,D15<1.3,E15>4),"Amber","Green")) -> Amber | G15: =IF(C15>=30,"DPD deterioration",IF(D15<1.1,"DSCR weakness",IF(E15>5,"High leverage","Normal"))) -> Normal
... A253: ='02_Loan_Portfolio'!A251 -> LN00250 | B253: ='02_Loan_Portfolio'!E251 -> BB | C253: ='02_Loan_Portfolio'!L251 -> 0 | D253: ='02_Loan_Portfolio'!J251 -> 2.018 | E253: ='02_Loan_Portfolio'!K251 -> 5.346 | F253: =IF(OR(C253>=30,D253<1.1,E253>5),"Red",IF(OR(C253>0,D253<1.3,E253>4),"Amber","Green")) -> Red | G253: =IF(C253>=30,"DPD deterioration",IF(D253<1.1,"DSCR weakness",IF(E253>5,"High leverage","Normal"))) -> High leverage

Sheet 07_Model_Validation
A1: Model Validation Dashboard
A3: Validation Area | B3: Metric | C3: Threshold | D3: Prototype Result | E3: Status | F3: Owner
A4: Discrimination | B4: AUC | C4: > 0.70 | D4: 0.78 | E4: Pass | F4: Model Risk
A5: Discrimination | B5: Gini | C5: > 0.40 | D5: =2*D4-1 -> 0.56 | E5: Pass | F5: Model Risk
A6: Separation | B6: KS | C6: > 0.30 | D6: 0.42 | E6: Pass | F6: Model Risk
A7: Stability | B7: PSI | C7: < 0.10 | D7: 0.08 | E7: Pass | F7: Model Monitoring
A8: Calibration | B8: Brier Score | C8: Lower is better | D8: 0.09 | E8: Monitor | F8: Model Risk
A9: Governance | B9: Documentation | C9: Complete | D9: Yes | E9: Pass | F9: Risk Governance

Sheet 08_Dashboard
A1: Executive Credit Risk Dashboard
A3: Total EAD VND | B3: =SUM('02_Loan_Portfolio'!P2:P251) -> 427296172686485
A4: Total ECL VND | B4: =SUM('04_IFRS9_ECL'!H2:H251) -> 2.9558725e+13
A5: Weighted Avg PD | B5: =SUMPRODUCT('02_Loan_Portfolio'!N2:N251,'02_Loan_Portfolio'!P2:P251)/SUM('02_Loan_Portfolio'!P2:P251) -> 0.08888751
A6: Weighted Avg LGD | B6: =SUMPRODUCT('02_Loan_Portfolio'!O2:O251,'02_Loan_Portfolio'!P2:P251)/SUM('02_Loan_Portfolio'!P2:P251) -> 0.55041643
A7: Stage 2 Ratio | B7: =SUMIF('02_Loan_Portfolio'!Q2:Q251,2,'02_Loan_Portfolio'!P2:P251)/SUM('02_Loan_Portfolio'!P2:P251) -> 0.24381359
A8: Stage 3 / NPL Ratio | B8: =SUMIF('02_Loan_Portfolio'!Q2:Q251,3,'02_Loan_Portfolio'!P2:P251)/SUM('02_Loan_Portfolio'!P2:P251) -> 0.010802926
A9: Severe Stress ECL Increase | B9: ='05_Stress_Test'!F12 -> 1.47
A10: Management Action | B10: ="Tighten monitoring for Stage 2, high DPD, weak DSCR and high leverage borrowers" -> Tighten monitoring for Stage 2, high DPD, weak DSCR and high leverage borrowers
A12: Scenario | B12: Stressed PD | C12: Stressed LGD | D12: Stressed ECL VND
A13: ='05_Stress_Test'!A10 -> Base | B13: ='05_Stress_Test'!B10 -> 0.08888751 | C13: ='05_Stress_Test'!C10 -> 0.55041643 | D13: ='05_Stress_Test'!E10 -> 2.0905528e+13
A14: ='05_Stress_Test'!A11 -> Mild Stress | B14: ='05_Stress_Test'!B11 -> 0.11999814 | C14: ='05_Stress_Test'!C11 -> 0.60545808 | D14: ='05_Stress_Test'!E11 -> 3.1044709e+13
A15: ='05_Stress_Test'!A12 -> Severe Stress | B15: ='05_Stress_Test'!B12 -> 0.16888627 | C15: ='05_Stress_Test'!C12 -> 0.71554136 | D15: ='05_Stress_Test'!E12 -> 5.1636653e+13

Sheet 09_Governance
A1: Model Governance Pack
A3: Section | B3: Content
A4: Model objective | B4: Estimate portfolio credit risk, IFRS9 ECL, stress impact and management actions.
A5: Model owner | B5: Credit Risk Analytics and Modelling team.
A6: Model type | B6: PD / LGD / EAD analytics, IFRS9 ECL engine, early warning, macro stress testing.
A7: Data limitation | B7: Synthetic data for interview demonstration. Replace with audited bank data for production.
A8: Validation | B8: AUC, Gini, KS, PSI, calibration, backtesting, override monitoring.
A9: Approval workflow | B9: Developer -> Validator -> Model Risk Committee -> CRO / Risk Committee.
A10: Monitoring frequency | B10: Monthly performance monitoring; quarterly recalibration review.

Sheet 10_Sources
A1: Topic | B1: URL | C1: Use
A2: Vietnam GDP growth | B2: https://data.worldbank.org/indicator/NY.GDP.MKTP.KD.ZG?locations=VN | C2: Historical public macro reference
A3: State Bank of Vietnam | B3: https://www.sbv.gov.vn | C3: Policy rate / banking sector public reference
A4: IFRS Foundation IFRS 9 | B4: https://www.ifrs.org/issued-standards/list-of-standards/ifrs-9-financial-instruments/ | C4: IFRS9 conceptual reference
A5: BIS Basel framework | B5: https://www.bis.org/basel_framework/ | C5: Basel credit risk and model governance reference
A6: Note | B6: Loan-level data is synthetic | C6: Bank internal loan-level data is not public
